bashguard/__init__.py
bashguard/__main__.py
bashguard/analyzers/__init__.py
bashguard/analyzers/analyzer.py
bashguard/analyzers/command_injection.py
bashguard/analyzers/environment.py
bashguard/analyzers/parameter_expansion.py
bashguard/analyzers/shellcheck_analyzer.py
bashguard/analyzers/variable_expansion.py
bashguard/core/__init__.py
bashguard/core/base_analyzer.py
bashguard/core/base_fixer.py
bashguard/core/logger.py
bashguard/core/reporter.py
bashguard/core/tsparser.py
bashguard/core/types.py
bashguard/core/vulnerability.py
bashguard/fixers/__init__.py
bashguard/fixers/command_substitution_fixer.py
bashguard/fixers/fixer.py
bashguard/fixers/variable_expansion_fixer.py
bashguard/tests/__init__.py
bashguard/tests/test_0th_expansion_no_vuln.py
bashguard/tests/test_array_index_attack.py
bashguard/tests/test_assignemnt_in_command_context_no_vuln.py
bashguard/tests/test_assignemnt_in_command_context_vuln.py
bashguard/tests/test_command_injection.py
bashguard/tests/test_command_injection_read.py
bashguard/tests/test_get_tainted_variables.py
bashguard/tests/test_indirect_command_injection.py
bashguard/tests/test_lasha.py
bashguard/tests/test_missing_path.py
bashguard/tests/test_parameter_expansion.py
bashguard/tests/test_parser.py
bashguard/tests/test_recursive_command_injection.py
bashguard/tests/test_recursive_variable_expansion.py
bashguard/tests/test_shellcheck_analyzer.py
bashguard/tests/test_subscript_detection.py
bashguard/tests/test_superweapon.py
bashguard/tests/test_unqoted_variable.py
bashguard/tests/test_variable_assignment_context.py
bashguard/tests/pwn_college_scripts/__init__.py
bashguard/tests/pwn_college_scripts/test_enigma_of_the_environment.py
bashguard/tests/pwn_college_scripts/test_ferocious_functionality.py
bashguard/tests/pwn_college_scripts/test_globbing_harmony.py
bashguard/tests/pwn_college_scripts/test_index_of_insanity.py
bashguard/tests/pwn_college_scripts/test_masquerade_of_the_self.py
bashguard-1.0.1.dist-info/METADATA
bashguard-1.0.1.dist-info/WHEEL
bashguard-1.0.1.dist-info/entry_points.txt
bashguard-1.0.1.dist-info/top_level.txt
bashguard-1.0.1.dist-info/RECORD
